mkdocs_sample_plugin/__init__.py
mkdocs_sample_plugin/plugin.py
mkdocs_sample_plugin-0.1.2.dist-info/METADATA
mkdocs_sample_plugin-0.1.2.dist-info/WHEEL
mkdocs_sample_plugin-0.1.2.dist-info/entry_points.txt
mkdocs_sample_plugin-0.1.2.dist-info/top_level.txt
mkdocs_sample_plugin-0.1.2.dist-info/RECORD
