Metadata-Version: 2.1
Name: mkdocs-sample-plugin
Version: 0.1.2
Summary: A sample MkDocs plugin to add custom text to the markdown pages.
Home-page: https://github.com/andynameistaken/mkdocs_sample_plugin
Author: Andrzej Zahorski
Author-email: andrzej.zahorski@gmail.com
Classifier: Framework :: MkDocs
Classifier: License :: OSI Approved :: MIT License
Classifier: Programming Language :: Python :: 3
Classifier: Programming Language :: Python :: 3.7
Classifier: Programming Language :: Python :: 3.8
Classifier: Programming Language :: Python :: 3.9
Requires-Python: >=3.7
Requires-Dist: mkdocs >=1.0
